{"store_id": "1028", "geofence_id": 1028, "rest_brId": 54943, "area_name": "Nishat Commercial Area", "city": "Karachi", "latitude": "24.800010121066183", "longitude": "67.05769388228225", "address": "Nishat Commercial Area", "state": "Sindh", "zipcode": "N/A", "geofence": "[24.80092788487597, 67.05764104762261],[24.79943775952391, 67.05954541602318],[24.79747037705657, 67.05762495436852],[24.79895565631158, 67.05569912829583]", "min_order": 500, "delivery_charges": 300, "max_delivery_time": 180, "start_time": "00:00:00", "end_time": "23:59:59", "formatted_start_time": "12:00 AM", "formatted_end_time": "11:59 PM"}