{"store_id": "2536", "geofence_id": 2536, "rest_brId": 54934, "area_name": "Hira Terrace", "city": "Karachi", "latitude": "24.884932857375578", "longitude": "67.06337530000008", "address": "Hira Terrace", "state": "Sindh", "zipcode": "N/A", "geofence": "[24.885231326951686, 67.06340152600512],[24.88506465451317, 67.06367242911563],[24.88479700487125, 67.06346455791697],[24.884964894259884, 67.06320304253802]", "min_order": 500, "delivery_charges": 199, "max_delivery_time": 180, "start_time": "00:00:00", "end_time": "23:59:59", "formatted_start_time": "12:00 AM", "formatted_end_time": "11:59 PM"}